boj/entry.py
boj/commands/add_cmd.py
boj/commands/test_cmd.py
boj/core/console.py
boj/core/file_io.py
boj/core/solved.py
boj/errors/error.py
boj/settings/language.json
boj/settings/level.json
boj_toolkit-0.1.5a0.dist-info/LICENSE.txt
boj_toolkit-0.1.5a0.dist-info/METADATA
boj_toolkit-0.1.5a0.dist-info/WHEEL
boj_toolkit-0.1.5a0.dist-info/entry_points.txt
boj_toolkit-0.1.5a0.dist-info/top_level.txt
boj_toolkit-0.1.5a0.dist-info/RECORD
