Metadata-Version: 2.1
Name: boj-toolkit
Version: 0.1.5a0
Summary: Command line interface for baekjoon online judge
Author-email: RedBe-an <redbean.of@gmail.com>
Keywords: boj,baekjoon,cli,boj-cli
Classifier: Development Status :: 3 - Alpha
Classifier: Intended Audience :: Developers
Classifier: Operating System :: Microsoft :: Windows :: Windows 11
Classifier: License :: OSI Approved :: MIT License
Classifier: Programming Language :: Python :: 3.12
Requires-Python: >=3.12
License-File: LICENSE.txt
Requires-Dist: beautifulsoup4 (==4.11.1)
Requires-Dist: requests (==2.28.2)
Requires-Dist: rich (==13.2.0)
